file_generation/__init__.py
file_generation/core.py
file_generation/generators.py
file_generation-0.2.5.dist-info/LICENSE
file_generation-0.2.5.dist-info/METADATA
file_generation-0.2.5.dist-info/WHEEL
file_generation-0.2.5.dist-info/top_level.txt
file_generation-0.2.5.dist-info/RECORD
