Metadata-Version: 2.2
Name: file-generation
Version: 0.2.5
Summary: A package for generating DOCX and XLSX files and zipping them.
Author-email: Gnel Sedrakyan <gnel@sedrakyan.am>
License: MIT License
Project-URL: Homepage, https://github.com/SedrakyanGnel/file-generation
Project-URL: Documentation, https://github.com/SedrakyanGnel/file-generation#readme
Project-URL: Source, https://github.com/SedrakyanGnel/file-generation
Project-URL: Issues, https://github.com/SedrakyanGnel/file-generation/issues
Keywords: docx,xlsx,file-generation,templating,zip
Classifier: Development Status :: 4 - Beta
Classifier: Intended Audience :: Developers
Classifier: License :: OSI Approved :: MIT License
Classifier: Programming Language :: Python :: 3
Classifier: Programming Language :: Python :: 3.7
Classifier: Programming Language :: Python :: 3.8
Classifier: Programming Language :: Python :: 3.9
Classifier: Programming Language :: Python :: 3.10
Classifier: Programming Language :: Python :: 3.11
Classifier: Operating System :: OS Independent
Requires-Python: >=3.7
License-File: LICENSE
Requires-Dist: docxtpl>=0.12.0
Requires-Dist: openpyxl>=3.0.0
Provides-Extra: dev
Requires-Dist: pytest>=6.0.0; extra == "dev"
Requires-Dist: black>=22.0.0; extra == "dev"
Requires-Dist: flake8>=4.0.0; extra == "dev"
Provides-Extra: docs
Requires-Dist: mkdocs>=1.0.0; extra == "docs"
Requires-Dist: mkdocs-material>=8.0.0; extra == "docs"
